automl_tools/__init__.py
automl_tools/functions/__init__.py
automl_tools/functions/imputation.py
automl_tools/functions/logger.py
automl_tools/functions/main.py
automl_tools/functions/modeling.py
automl_tools/functions/optimization_binary.py
automl_tools/functions/optimization_multi_class.py
automl_tools/functions/optimization_regression.py
automl_tools/functions/parameter.py
automl_tools/functions/prepare.py
automl_tools/functions/processing.py
automl_tools/functions/selection.py
automl_tools/functions/utils.py
automl_tools-0.2.5.dist-info/LICENSE
automl_tools-0.2.5.dist-info/METADATA
automl_tools-0.2.5.dist-info/WHEEL
automl_tools-0.2.5.dist-info/top_level.txt
automl_tools-0.2.5.dist-info/RECORD
