Metadata-Version: 2.1
Name: automl-tools
Version: 0.2.5
Summary: automl_tools
Home-page: https://github.com/jonaqp/automl_tools
Author: Jonathan Quiza
Author-email: jony327@gmail.com
License: UNKNOWN
Download-URL: https://github.com/jonaqp/automl_tools/archive/main.zip
Keywords: automl
Platform: UNKNOWN
Classifier: Development Status :: 5 - Production/Stable
Classifier: Intended Audience :: Developers
Classifier: Intended Audience :: Science/Research
Classifier: Topic :: Scientific/Engineering :: Artificial Intelligence
Classifier: License :: OSI Approved :: Apache Software License
Classifier: Programming Language :: Python :: 3.9
License-File: LICENSE
Requires-Dist: certifi (==2024.2.2)
Requires-Dist: scikit-learn (==1.2.2)
Requires-Dist: numpy (==1.25.2)
Requires-Dist: pandas (==1.5.3)
Requires-Dist: prettytable (==3.10.0)
Requires-Dist: optbinning (==0.19.0)
Requires-Dist: psutil (==5.9.8)
Requires-Dist: xgboost (==2.0.3)
Requires-Dist: lightgbm (==4.1.0)
Requires-Dist: catboost (==1.2.3)
Requires-Dist: category-encoders (==2.6.3)
Requires-Dist: ngboost (==0.3.7)
Requires-Dist: hyperopt (==0.2.7)
Requires-Dist: seaborn (==0.13.1)
Requires-Dist: colorama (==0.4.6)
Requires-Dist: tabulate (==0.9.0)
Requires-Dist: wheel (==0.40)
Requires-Dist: setuptools (==58.2.0)
